{
  "url": "https://liturgia.wiara.pl/doc/414208.Piatek-33-tydzien-zwykly-Rok-II",
  "tytul_dnia": "Piątek, 33 tydzień zwykły, Rok II",
  "czytania": [
    {
      "typ": "PSALM RESPONSORYJNY",
      "sigla": "Ps 119 (118), 14 i 24. 72 i 103. 111 i 131 (R.: por. 103)",
      "opis": "",
      "tekst": "Refren: Nad miód są słodsze Twoje przykazania.\nWięcej się cieszę z drogi wskazanej\nprzez Twe napomnienia *\nniż z wszelkiego bogactwa.\nBo Twe napomnienia są moją rozkoszą, *\nmoimi doradcami Twoje ustawy.\nRefren.\nPrawo ust Twoich jest dla mnie lepsze *\nniż tysiące sztuk złota i srebra.\nJak słodka jest Twoja mowa dla mego podniebienia, *\nponad miód słodsza dla ust moich.\nRefren.\nNapomnienia Twoje są moim dziedzictwem na wieki, *\nbo są radością mojego serca.\nZaczerpnę powietrza otwartymi ustami, *\nbo pragnę Twoich przykazań.\nRefren."
    },
    {
      "typ": "AKLAMACJA",
      "sigla": "Por. J 10, 27",
      "opis": "Aklamacja: Alleluja, alleluja, alleluja.",
      "tekst": "Moje owce słuchają mego głosu,\nJa znam je, a one idą za Mną."
    },
    {
      "typ": "EWANGELIA",
      "sigla": "Łk 19, 45-48",
      "opis": "",
      "tekst": "Jezus wypędza przekupniów ze świątyni\nJezus wszedł do świątyni i zaczął wyrzucać sprzedających w niej. Mówił do nich: «Napisane jest: „Mój dom będzie domem modlitwy”, a wy uczyniliście go jaskinią zbójców».\nI nauczał codziennie w świątyni. Lecz arcykapłani i uczeni w Piśmie oraz przywódcy ludu czyhali na Jego życie. Tylko nie wiedzieli, co by mogli uczynić, cały lud bowiem słuchał Go z zapartym tchem.\nOto słowo Pańskie."
    }
  ]
}